{
  "workbench.colorCustomizations": {
    "focusBorder": "#fbba73",
    "foreground": "#eee0d5",
    "editor.background": "#19120c",
    "editor.foreground": "#eee0d5",
    "editorLineNumber.foreground": "#d5c4b5",
    "editorLineNumber.activeForeground": "#fbba73",
    "editorCursor.foreground": "#fbba73",
    "editor.selectionBackground": "#683d0080",
    "editor.inactiveSelectionBackground": "#50453a60",
    "sideBar.background": "#251e17",
    "sideBar.foreground": "#eee0d5",
    "sideBar.border": "#9d8e81",
    "sideBarTitle.foreground": "#eee0d5",
    "sideBarSectionHeader.background": "#302921",
    "sideBarSectionHeader.foreground": "#eee0d5",
    "activityBar.background": "#251e17",
    "activityBar.foreground": "#eee0d5",
    "activityBar.inactiveForeground": "#d5c4b5",
    "activityBar.activeBorder": "#fbba73",
    "activityBarBadge.background": "#fbba73",
    "activityBarBadge.foreground": "#492900",
    "statusBar.background": "#211a14",
    "statusBar.foreground": "#eee0d5",
    "statusBar.border": "#9d8e81",
    "statusBar.noFolderBackground": "#211a14",
    "titleBar.activeBackground": "#251e17",
    "titleBar.activeForeground": "#eee0d5",
    "titleBar.inactiveBackground": "#251e17",
    "titleBar.inactiveForeground": "#d5c4b5",
    "titleBar.border": "#9d8e81",
    "tab.activeBackground": "#19120c",
    "tab.activeForeground": "#eee0d5",
    "tab.activeBorder": "#fbba73",
    "tab.inactiveBackground": "#251e17",
    "tab.inactiveForeground": "#d5c4b5",
    "tab.border": "#9d8e81",
    "panel.background": "#19120c",
    "panel.border": "#9d8e81",
    "panelTitle.activeBorder": "#fbba73",
    "panelTitle.activeForeground": "#eee0d5",
    "panelTitle.inactiveForeground": "#d5c4b5",
    "list.activeSelectionBackground": "#683d00",
    "list.activeSelectionForeground": "#ffdcbc",
    "list.inactiveSelectionBackground": "#50453a",
    "list.hoverBackground": "#3b332c",
    "list.focusOutline": "#fbba73",
    "button.background": "#fbba73",
    "button.foreground": "#492900",
    "button.hoverBackground": "#683d00",
    "input.background": "#3b332c",
    "input.foreground": "#eee0d5",
    "input.border": "#9d8e81",
    "input.placeholderForeground": "#d5c4b5",
    "terminal.foreground": "#eee0d5",
    "terminal.background": "#19120c",
    "terminal.ansiBlack": "#211a14",
    "terminal.ansiRed": "#ffb4ab",
    "terminal.ansiGreen": "#becc9c",
    "terminal.ansiYellow": "#e0c1a3",
    "terminal.ansiBlue": "#fbba73",
    "terminal.ansiMagenta": "#becc9c",
    "terminal.ansiCyan": "#e0c1a3",
    "terminal.ansiWhite": "#eee0d5",
    "notificationCenter.border": "#9d8e81",
    "notifications.background": "#251e17",
    "notifications.foreground": "#eee0d5",
    "notifications.border": "#9d8e81"
  }
}
